pacurses/constants/button_names.py
pacurses/constants/menu_names.py
pacurses/constants/palette_names.py
pacurses/constants/sink_types.py
pacurses/constants/state_keys.py
pacurses/gui/abbreviation.py
pacurses/gui/footer.py
pacurses/gui/header.py
pacurses/gui/menus/default.py
pacurses/gui/menus/help.py
pacurses/gui/menus/main.py
pacurses/gui/menus/menu.py
pacurses/gui/menus/mute.py
pacurses/gui/menus/utils.py
pacurses/gui/menus/volume.py
pacurses/gui/palette.py
pacurses/gui/status.py
pacurses/gui/widgets/sink_progress_bar.py
pacurses/gui/widgets/volume_slider.py
pacurses/main.py
pacurses/pulse_audio/external.py
pacurses/pulse_audio/information.py
pacurses/pulse_audio/input.py
pacurses/pulse_audio/output.py
pacurses/pulse_audio/sink.py
pacurses/pulse_audio/utils.py
pacurses-0.1.1.dist-info/entry_points.txt
pacurses-0.1.1.dist-info/WHEEL
pacurses-0.1.1.dist-info/METADATA
pacurses-0.1.1.dist-info/RECORD
